README
setup.py
pybencoding/__init__.py
pybencoding.egg-info/PKG-INFO
pybencoding.egg-info/SOURCES.txt
pybencoding.egg-info/dependency_links.txt
pybencoding.egg-info/top_level.txt