Metadata-Version: 1.1
Name: pybencoding
Version: 0.1.1
Summary: A simple python3 implementation of bittorrent's bencoding.
Home-page: https://gitlab.com/clueless/pybencoding
Author: clueless
Author-email: clueless@thunked.org
License: MIT
Keywords: bittorrent bencode
Platform: UNKNOWN
Classifier: Development Status :: 4 - Beta
Classifier: Intended Audience :: Developers
Classifier: Topic :: Software Development :: Libraries :: Python Modules
Classifier: License :: OSI Approved :: MIT License
Classifier: Programming Language :: Python :: 3
Classifier: Programming Language :: Python :: 3 :: Only
Classifier: Programming Language :: Python :: 3.3
Classifier: Programming Language :: Python :: 3.4
Classifier: Programming Language :: Python :: 3.5
